ape/__init__.py
ape/_typing.py
ape/_version.py
ape/optimization/__init__.py
ape/optimization/evolution_strategy.py
ape/tests/test_evolution_strategy.py
ape/tests/test_read_me.py
ape_ai-0.1.3.dist-info/METADATA
ape_ai-0.1.3.dist-info/WHEEL
ape_ai-0.1.3.dist-info/top_level.txt
ape_ai-0.1.3.dist-info/RECORD
