Metadata-Version: 2.1
Name: ape-ai
Version: 0.1.3
Summary: A Python framework for AI
Author-email: Guilherme Kowalczuk <guilhermekowalczuk@gmail.com>
Project-URL: repository, https://github.com/kowalks/ape-ai
Classifier: Topic :: Scientific/Engineering
Requires-Python: >=3.11
Requires-Dist: numpy
Requires-Dist: tqdm
Provides-Extra: all
Requires-Dist: matplotlib ; extra == 'all'
Requires-Dist: ffmpeg-python ; extra == 'all'
Requires-Dist: pytest ; extra == 'all'
Provides-Extra: test
Requires-Dist: pytest ; extra == 'test'
